numeric_grad/__init__.py
numeric_grad/numeric_grad.py
numeric_grad-0.0.4.dist-info/METADATA
numeric_grad-0.0.4.dist-info/WHEEL
numeric_grad-0.0.4.dist-info/top_level.txt
numeric_grad-0.0.4.dist-info/RECORD
